coffeanalyzer/__init__.py
coffeanalyzer/coffeanalyzer.py
coffe_analyzer-1.0.2.dist-info/METADATA
coffe_analyzer-1.0.2.dist-info/WHEEL
coffe_analyzer-1.0.2.dist-info/licenses/LICENSE
coffe_analyzer-1.0.2.dist-info/RECORD
