Metadata-Version: 2.3
Name: coffe-analyzer
Version: 1.0.2
Summary: Supports the CoFFE analysis presented in ARP4761A/ED-135.
Project-URL: Repository, https://github.com/samuelglorente/coffe_analyzer.git
Project-URL: Issues, https://github.com/samuelglorente/coffe_analyzer/issues
Author-email: Samuel Garcia Lorente <sglorente@proton.me>
License:                     GNU GENERAL PUBLIC LICENSE
License-File: LICENSE
Keywords: ARP4761A,CoFFE,ED135,RAMS,safety
Classifier: Development Status :: 3 - Alpha
Classifier: Programming Language :: Python
Requires-Python: >=3.10
Requires-Dist: mpmath==1.3.0
Requires-Dist: numpy==1.26.4
Requires-Dist: pandas==2.2.2
Requires-Dist: python-dateutil==2.9.0.post0
Requires-Dist: pytz==2024.1
Requires-Dist: six==1.16.0
Requires-Dist: sympy==1.12
Requires-Dist: tzdata==2024.1
